AUTHORS.rst
CONTRIBUTING.rst
HISTORY.rst
LICENSE
MANIFEST.in
README.rst
setup.py
keychain_manager/__init__.py
keychain_manager/keychain_manager.py
keychain_manager.egg-info/PKG-INFO
keychain_manager.egg-info/SOURCES.txt
keychain_manager.egg-info/dependency_links.txt
keychain_manager.egg-info/not-zip-safe
keychain_manager.egg-info/top_level.txt