Metadata-Version: 1.1
Name: keychain-manager
Version: 0.1.2
Summary: A Python API for Mac OS X Keychain, port of https://github.com/jprichardson/keychain_manager
Home-page: https://github.com/zen4ever/keychain_manager
Author: Andrii Kurinnyi
Author-email: andrew@marpasoft.com
License: BSD
Keywords: keychain_manager
Platform: UNKNOWN
Classifier: Development Status :: 2 - Pre-Alpha
Classifier: Intended Audience :: Developers
Classifier: License :: OSI Approved :: BSD License
Classifier: Natural Language :: English
Classifier: Programming Language :: Python :: 2
Classifier: Programming Language :: Python :: 2.6
Classifier: Programming Language :: Python :: 2.7
Classifier: Programming Language :: Python :: 3
Classifier: Programming Language :: Python :: 3.3
